datapizza/clients/mistral/__init__.py
datapizza/clients/mistral/memory_adapter.py
datapizza/clients/mistral/mistral_client.py
datapizza_ai_clients_mistral-0.0.4.dist-info/METADATA
datapizza_ai_clients_mistral-0.0.4.dist-info/WHEEL
datapizza_ai_clients_mistral-0.0.4.dist-info/RECORD
